tracemoe/ATraceMoe.py
tracemoe/TraceMoe.py
tracemoe/__init__.py
tracemoe-1.0.dist-info/METADATA
tracemoe-1.0.dist-info/WHEEL
tracemoe-1.0.dist-info/top_level.txt
tracemoe-1.0.dist-info/RECORD
